pbctools/__init__.py
pbctools/core.py
pbctools/_cpp/bindings.cpp
pbctools/_cpp/pbctools_cpp.cpp
pbctools/_cpp/pbctools_cpp.cpython-39-x86_64-linux-gnu.so
pbctools/_cpp/pbctools_cpp.h
pbctools-0.2.0.dist-info/METADATA
pbctools-0.2.0.dist-info/WHEEL
pbctools-0.2.0.dist-info/top_level.txt
pbctools-0.2.0.dist-info/RECORD
pbctools-0.2.0.dist-info/licenses/LICENSE
pbctools.libs/libgomp-a34b3233.so.1.0.0
