Metadata-Version: 2.4
Name: pbctools
Version: 0.2.0
Summary: Lightweight PBC analysis toolkit for molecular simulations
Author-email: Jonas Hänseroth <jonas.haenseroth@tu-ilmenau.de>
License: MIT
Project-URL: Homepage, https://github.com/jhaens/pbctools
Project-URL: Repository, https://github.com/jhaens/pbctools.git
Project-URL: Bug Tracker, https://github.com/jhaens/pbctools/issues
Keywords: molecular dynamics,PBC,periodic boundary conditions,trajectory analysis
Classifier: Development Status :: 4 - Beta
Classifier: Intended Audience :: Science/Research
Classifier: License :: OSI Approved :: MIT License
Classifier: Programming Language :: Python :: 3
Classifier: Programming Language :: Python :: 3.8
Classifier: Programming Language :: Python :: 3.9
Classifier: Programming Language :: Python :: 3.10
Classifier: Programming Language :: Python :: 3.11
Classifier: Programming Language :: C++
Classifier: Topic :: Scientific/Engineering :: Chemistry
Classifier: Topic :: Scientific/Engineering :: Physics
Requires-Python: >=3.8
License-File: LICENSE
Requires-Dist: numpy>=1.20.0
Provides-Extra: dev
Requires-Dist: pytest>=6.0; extra == "dev"
Requires-Dist: pytest-cov; extra == "dev"
Requires-Dist: black; extra == "dev"
Requires-Dist: flake8; extra == "dev"
Requires-Dist: mypy; extra == "dev"
Provides-Extra: docs
Requires-Dist: sphinx; extra == "docs"
Requires-Dist: sphinx-rtd-theme; extra == "docs"
Dynamic: license-file
Dynamic: requires-python
